iac_init/__init__.py
iac_init/__main__.py
iac_init/cli/main.py
iac_init/cli/options.py
iac_init/conf/__init__.py
iac_init/conf/global_settings.py
iac_init/scripts/ansible_tool.py
iac_init/scripts/apic_connecton_tool.py
iac_init/scripts/cimc_precheck_tool.py
iac_init/scripts/logging_tool.py
iac_init/scripts/ssh_tool.py
iac_init/scripts/telnet_tool.py
iac_init/scripts/thread_tool.py
iac_init/templates/01-wipe_aci_fabric/aci_switch_reimage/files/aci_switch_reiamge.sh
iac_init/templates/01-wipe_aci_fabric/aci_switch_reimage/files/aci_switch_reiamge_sh_base64
iac_init/templates/01-wipe_aci_fabric/aci_switch_reimage/tasks/main.yml
iac_init/templates/01-wipe_aci_fabric/aci_switch_reimage/templates/aci_switch_reimage.exp.jinja2
iac_init/templates/01-wipe_aci_fabric/aci_switch_reimage/templates/aci_switch_reimage_post_check.exp.jinja2
iac_init/templates/01-wipe_aci_fabric/aci_switch_reimage/vars/.gitkeep
iac_init/templates/01-wipe_aci_fabric/apic_reimage/files/.gitkeep
iac_init/templates/01-wipe_aci_fabric/apic_reimage/tasks/main.yml
iac_init/templates/01-wipe_aci_fabric/apic_reimage/templates/apic_reimage4.exp.jinja2
iac_init/templates/01-wipe_aci_fabric/apic_reimage/templates/apic_reimage5.exp.jinja2
iac_init/templates/01-wipe_aci_fabric/apic_reimage/templates/apic_reimage6.exp.jinja2
iac_init/templates/01-wipe_aci_fabric/apic_reimage/templates/apic_reimage_post_check.exp.jinja2
iac_init/templates/01-wipe_aci_fabric/apic_reimage/vars/.gitkeep
iac_init/templates/01-wipe_aci_fabric/playbook_aci_switch_init.yaml
iac_init/templates/01-wipe_aci_fabric/playbook_apic_init.yaml
iac_init/templates/02-discover_apic/apic_discovery/files/.gitkeep
iac_init/templates/02-discover_apic/apic_discovery/tasks/main.yml
iac_init/templates/02-discover_apic/apic_discovery/templates/apic_discovery4.exp.jinja2
iac_init/templates/02-discover_apic/apic_discovery/templates/apic_discovery5.exp.jinja2
iac_init/templates/02-discover_apic/apic_discovery/templates/apic_discovery6.exp.jinja2
iac_init-0.9.64.dist-info/LICENSE
iac_init-0.9.64.dist-info/METADATA
iac_init-0.9.64.dist-info/WHEEL
iac_init-0.9.64.dist-info/entry_points.txt
iac_init-0.9.64.dist-info/RECORD
